{
  "For Pitts and Giggles": {
    "week_1": {
      "points_for": 103.24,
      "points_against": 143.2,
      "opponent": "Oscorps Buns"
    },
    "week_2": {
      "points_for": 108.66,
      "points_against": 95.0,
      "opponent": "The Sage's Playmakers"
    },
    "week_3": {
      "points_for": 136.32,
      "points_against": 94.0,
      "opponent": "Bumpin Brasnos"
    },
    "week_4": {
      "points_for": 130.1,
      "points_against": 92.18,
      "opponent": "Revy\u2019s Konstruction"
    },
    "week_5": {
      "points_for": 151.96,
      "points_against": 106.34,
      "opponent": "Room 40"
    },
    "week_6": {
      "points_for": 119.06,
      "points_against": 121.8,
      "opponent": "Sparty's Sigmas"
    },
    "week_7": {
      "points_for": 147.3,
      "points_against": 144.76,
      "opponent": "Lawrence & Order"
    },
    "week_8": {
      "points_for": 129.26,
      "points_against": 111.26,
      "opponent": "Oscorps Buns"
    },
    "week_9": {
      "points_for": 113.02,
      "points_against": 150.16,
      "opponent": "Tsuga\u2019s Tuck Shop"
    },
    "week_10": {
      "points_for": 77.28,
      "points_against": 88.0,
      "opponent": "Wicked Wah-Bams"
    },
    "week_11": {
      "points_for": 106.2,
      "points_against": 105.62,
      "opponent": "The Hunters"
    },
    "week_12": {
      "points_for": 145.26,
      "points_against": 101.96,
      "opponent": "Revy\u2019s Konstruction"
    },
    "week_13": {
      "points_for": 112.34,
      "points_against": 134.5,
      "opponent": "Supernova\u2019s Studs"
    },
    "week_14": {
      "points_for": 125.82,
      "points_against": 113.86,
      "opponent": "Sparty's Sigmas"
    },
    "week_16": {
      "points_for": 150.18,
      "points_against": 130.24,
      "opponent": "Lawrence & Order"
    },
    "week_17": {
      "points_for": 126.56,
      "points_against": 117.9,
      "opponent": "Wicked Wah-Bams"
    }
  },
  "Wicked Wah-Bams": {
    "week_1": {
      "points_for": 116.84,
      "points_against": 88.22,
      "opponent": "Supernova\u2019s Studs"
    },
    "week_2": {
      "points_for": 127.8,
      "points_against": 111.18,
      "opponent": "Room 40"
    },
    "week_3": {
      "points_for": 156.08,
      "points_against": 118.96,
      "opponent": "Tsuga\u2019s Tuck Shop"
    },
    "week_4": {
      "points_for": 116.72,
      "points_against": 82.6,
      "opponent": "The Sage's Playmakers"
    },
    "week_5": {
      "points_for": 122.24,
      "points_against": 133.02,
      "opponent": "Oscorps Buns"
    },
    "week_6": {
      "points_for": 139.04,
      "points_against": 131.78,
      "opponent": "Bumpin Brasnos"
    },
    "week_7": {
      "points_for": 121.86,
      "points_against": 83.4,
      "opponent": "Sparty's Sigmas"
    },
    "week_8": {
      "points_for": 106.7,
      "points_against": 129.66,
      "opponent": "Supernova\u2019s Studs"
    },
    "week_9": {
      "points_for": 94.2,
      "points_against": 126.28,
      "opponent": "The Hunters"
    },
    "week_10": {
      "points_for": 88.0,
      "points_against": 77.28,
      "opponent": "For Pitts and Giggles"
    },
    "week_11": {
      "points_for": 79.38,
      "points_against": 148.48,
      "opponent": "Lawrence & Order"
    },
    "week_12": {
      "points_for": 97.82,
      "points_against": 141.8,
      "opponent": "The Sage's Playmakers"
    },
    "week_13": {
      "points_for": 117.42,
      "points_against": 111.36,
      "opponent": "Revy\u2019s Konstruction"
    },
    "week_14": {
      "points_for": 113.94,
      "points_against": 94.74,
      "opponent": "Bumpin Brasnos"
    },
    "week_16": {
      "points_for": 126.3,
      "points_against": 117.54,
      "opponent": "The Hunters"
    },
    "week_17": {
      "points_for": 117.9,
      "points_against": 126.56,
      "opponent": "For Pitts and Giggles"
    }
  },
  "Lawrence & Order": {
    "week_1": {
      "points_for": 114.24,
      "points_against": 89.84,
      "opponent": "Tsuga\u2019s Tuck Shop"
    },
    "week_2": {
      "points_for": 128.84,
      "points_against": 86.06,
      "opponent": "Revy\u2019s Konstruction"
    },
    "week_3": {
      "points_for": 116.26,
      "points_against": 182.92,
      "opponent": "Sparty's Sigmas"
    },
    "week_4": {
      "points_for": 97.98,
      "points_against": 92.02,
      "opponent": "The Hunters"
    },
    "week_5": {
      "points_for": 62.0,
      "points_against": 108.62,
      "opponent": "Supernova\u2019s Studs"
    },
    "week_6": {
      "points_for": 119.54,
      "points_against": 127.82,
      "opponent": "Room 40"
    },
    "week_7": {
      "points_for": 144.76,
      "points_against": 147.3,
      "opponent": "For Pitts and Giggles"
    },
    "week_8": {
      "points_for": 128.48,
      "points_against": 120.36,
      "opponent": "Tsuga\u2019s Tuck Shop"
    },
    "week_9": {
      "points_for": 84.8,
      "points_against": 93.9,
      "opponent": "The Sage's Playmakers"
    },
    "week_10": {
      "points_for": 144.5,
      "points_against": 122.92,
      "opponent": "Bumpin Brasnos"
    },
    "week_11": {
      "points_for": 148.48,
      "points_against": 79.38,
      "opponent": "Wicked Wah-Bams"
    },
    "week_12": {
      "points_for": 136.36,
      "points_against": 131.6,
      "opponent": "The Hunters"
    },
    "week_13": {
      "points_for": 116.92,
      "points_against": 121.92,
      "opponent": "Oscorps Buns"
    },
    "week_14": {
      "points_for": 118.06,
      "points_against": 144.24,
      "opponent": "Room 40"
    },
    "week_15": {
      "points_for": 172.86,
      "points_against": 90.96,
      "opponent": "Tsuga\u2019s Tuck Shop"
    },
    "week_16": {
      "points_for": 130.24,
      "points_against": 150.18,
      "opponent": "For Pitts and Giggles"
    },
    "week_17": {
      "points_for": 101.46,
      "points_against": 99.56,
      "opponent": "The Hunters"
    }
  },
  "The Hunters": {
    "week_1": {
      "points_for": 104.56,
      "points_against": 76.16,
      "opponent": "Room 40"
    },
    "week_2": {
      "points_for": 135.54,
      "points_against": 101.2,
      "opponent": "Supernova\u2019s Studs"
    },
    "week_3": {
      "points_for": 130.54,
      "points_against": 112.86,
      "opponent": "Revy\u2019s Konstruction"
    },
    "week_4": {
      "points_for": 92.02,
      "points_against": 97.98,
      "opponent": "Lawrence & Order"
    },
    "week_5": {
      "points_for": 62.66,
      "points_against": 102.28,
      "opponent": "Bumpin Brasnos"
    },
    "week_6": {
      "points_for": 95.74,
      "points_against": 94.62,
      "opponent": "Tsuga\u2019s Tuck Shop"
    },
    "week_7": {
      "points_for": 117.66,
      "points_against": 80.66,
      "opponent": "Oscorps Buns"
    },
    "week_8": {
      "points_for": 103.36,
      "points_against": 105.98,
      "opponent": "Room 40"
    },
    "week_9": {
      "points_for": 126.28,
      "points_against": 94.2,
      "opponent": "Wicked Wah-Bams"
    },
    "week_10": {
      "points_for": 138.66,
      "points_against": 178.68,
      "opponent": "Sparty's Sigmas"
    },
    "week_11": {
      "points_for": 105.62,
      "points_against": 106.2,
      "opponent": "For Pitts and Giggles"
    },
    "week_12": {
      "points_for": 131.6,
      "points_against": 136.36,
      "opponent": "Lawrence & Order"
    },
    "week_13": {
      "points_for": 133.36,
      "points_against": 93.78,
      "opponent": "The Sage's Playmakers"
    },
    "week_14": {
      "points_for": 140.7,
      "points_against": 116.54,
      "opponent": "Tsuga\u2019s Tuck Shop"
    },
    "week_15": {
      "points_for": 115.1,
      "points_against": 93.62,
      "opponent": "Sparty's Sigmas"
    },
    "week_16": {
      "points_for": 117.54,
      "points_against": 126.3,
      "opponent": "Wicked Wah-Bams"
    },
    "week_17": {
      "points_for": 99.56,
      "points_against": 101.46,
      "opponent": "Lawrence & Order"
    }
  },
  "Sparty's Sigmas": {
    "week_1": {
      "points_for": 82.28,
      "points_against": 98.76,
      "opponent": "Revy\u2019s Konstruction"
    },
    "week_2": {
      "points_for": 140.68,
      "points_against": 115.9,
      "opponent": "Bumpin Brasnos"
    },
    "week_3": {
      "points_for": 182.92,
      "points_against": 116.26,
      "opponent": "Lawrence & Order"
    },
    "week_4": {
      "points_for": 122.54,
      "points_against": 123.26,
      "opponent": "Oscorps Buns"
    },
    "week_5": {
      "points_for": 119.68,
      "points_against": 206.88,
      "opponent": "Tsuga\u2019s Tuck Shop"
    },
    "week_6": {
      "points_for": 121.8,
      "points_against": 119.06,
      "opponent": "For Pitts and Giggles"
    },
    "week_7": {
      "points_for": 83.4,
      "points_against": 121.86,
      "opponent": "Wicked Wah-Bams"
    },
    "week_8": {
      "points_for": 162.72,
      "points_against": 112.46,
      "opponent": "Revy\u2019s Konstruction"
    },
    "week_9": {
      "points_for": 96.62,
      "points_against": 120.02,
      "opponent": "Supernova\u2019s Studs"
    },
    "week_10": {
      "points_for": 178.68,
      "points_against": 138.66,
      "opponent": "The Hunters"
    },
    "week_11": {
      "points_for": 163.84,
      "points_against": 113.04,
      "opponent": "The Sage's Playmakers"
    },
    "week_12": {
      "points_for": 114.2,
      "points_against": 153.4,
      "opponent": "Oscorps Buns"
    },
    "week_13": {
      "points_for": 150.34,
      "points_against": 121.16,
      "opponent": "Room 40"
    },
    "week_14": {
      "points_for": 113.86,
      "points_against": 125.82,
      "opponent": "For Pitts and Giggles"
    },
    "week_15": {
      "points_for": 93.62,
      "points_against": 115.1,
      "opponent": "The Hunters"
    },
    "week_16": {
      "points_for": 123.32,
      "points_against": 94.02,
      "opponent": "Tsuga\u2019s Tuck Shop"
    }
  },
  "Tsuga\u2019s Tuck Shop": {
    "week_1": {
      "points_for": 89.84,
      "points_against": 114.24,
      "opponent": "Lawrence & Order"
    },
    "week_2": {
      "points_for": 120.84,
      "points_against": 99.42,
      "opponent": "Oscorps Buns"
    },
    "week_3": {
      "points_for": 118.96,
      "points_against": 156.08,
      "opponent": "Wicked Wah-Bams"
    },
    "week_4": {
      "points_for": 146.6,
      "points_against": 138.22,
      "opponent": "Room 40"
    },
    "week_5": {
      "points_for": 206.88,
      "points_against": 119.68,
      "opponent": "Sparty's Sigmas"
    },
    "week_6": {
      "points_for": 94.62,
      "points_against": 95.74,
      "opponent": "The Hunters"
    },
    "week_7": {
      "points_for": 97.36,
      "points_against": 95.36,
      "opponent": "The Sage's Playmakers"
    },
    "week_8": {
      "points_for": 120.36,
      "points_against": 128.48,
      "opponent": "Lawrence & Order"
    },
    "week_9": {
      "points_for": 150.16,
      "points_against": 113.02,
      "opponent": "For Pitts and Giggles"
    },
    "week_10": {
      "points_for": 147.36,
      "points_against": 89.46,
      "opponent": "Supernova\u2019s Studs"
    },
    "week_11": {
      "points_for": 82.86,
      "points_against": 101.3,
      "opponent": "Revy\u2019s Konstruction"
    },
    "week_12": {
      "points_for": 121.44,
      "points_against": 111.28,
      "opponent": "Room 40"
    },
    "week_13": {
      "points_for": 142.26,
      "points_against": 131.28,
      "opponent": "Bumpin Brasnos"
    },
    "week_14": {
      "points_for": 116.54,
      "points_against": 140.7,
      "opponent": "The Hunters"
    },
    "week_15": {
      "points_for": 90.96,
      "points_against": 172.86,
      "opponent": "Lawrence & Order"
    },
    "week_16": {
      "points_for": 94.02,
      "points_against": 123.32,
      "opponent": "Sparty's Sigmas"
    }
  },
  "Bumpin Brasnos": {
    "week_1": {
      "points_for": 110.16,
      "points_against": 128.46,
      "opponent": "The Sage's Playmakers"
    },
    "week_2": {
      "points_for": 115.9,
      "points_against": 140.68,
      "opponent": "Sparty's Sigmas"
    },
    "week_3": {
      "points_for": 94.0,
      "points_against": 136.32,
      "opponent": "For Pitts and Giggles"
    },
    "week_4": {
      "points_for": 149.08,
      "points_against": 137.02,
      "opponent": "Supernova\u2019s Studs"
    },
    "week_5": {
      "points_for": 102.28,
      "points_against": 62.66,
      "opponent": "The Hunters"
    },
    "week_6": {
      "points_for": 131.78,
      "points_against": 139.04,
      "opponent": "Wicked Wah-Bams"
    },
    "week_7": {
      "points_for": 134.16,
      "points_against": 82.98,
      "opponent": "Room 40"
    },
    "week_8": {
      "points_for": 123.92,
      "points_against": 152.48,
      "opponent": "The Sage's Playmakers"
    },
    "week_9": {
      "points_for": 142.34,
      "points_against": 76.84,
      "opponent": "Revy\u2019s Konstruction"
    },
    "week_10": {
      "points_for": 122.92,
      "points_against": 144.5,
      "opponent": "Lawrence & Order"
    },
    "week_11": {
      "points_for": 147.7,
      "points_against": 136.34,
      "opponent": "Oscorps Buns"
    },
    "week_12": {
      "points_for": 137.18,
      "points_against": 108.12,
      "opponent": "Supernova\u2019s Studs"
    },
    "week_13": {
      "points_for": 131.28,
      "points_against": 142.26,
      "opponent": "Tsuga\u2019s Tuck Shop"
    },
    "week_14": {
      "points_for": 94.74,
      "points_against": 113.94,
      "opponent": "Wicked Wah-Bams"
    },
    "week_16": {
      "points_for": 149.62,
      "points_against": 83.5,
      "opponent": "Supernova\u2019s Studs"
    },
    "week_17": {
      "points_for": 144.26,
      "points_against": 107.34,
      "opponent": "Room 40"
    }
  },
  "Room 40": {
    "week_1": {
      "points_for": 76.16,
      "points_against": 104.56,
      "opponent": "The Hunters"
    },
    "week_2": {
      "points_for": 111.18,
      "points_against": 127.8,
      "opponent": "Wicked Wah-Bams"
    },
    "week_3": {
      "points_for": 141.18,
      "points_against": 53.96,
      "opponent": "The Sage's Playmakers"
    },
    "week_4": {
      "points_for": 138.22,
      "points_against": 146.6,
      "opponent": "Tsuga\u2019s Tuck Shop"
    },
    "week_5": {
      "points_for": 106.34,
      "points_against": 151.96,
      "opponent": "For Pitts and Giggles"
    },
    "week_6": {
      "points_for": 127.82,
      "points_against": 119.54,
      "opponent": "Lawrence & Order"
    },
    "week_7": {
      "points_for": 82.98,
      "points_against": 134.16,
      "opponent": "Bumpin Brasnos"
    },
    "week_8": {
      "points_for": 105.98,
      "points_against": 103.36,
      "opponent": "The Hunters"
    },
    "week_9": {
      "points_for": 159.48,
      "points_against": 99.08,
      "opponent": "Oscorps Buns"
    },
    "week_10": {
      "points_for": 78.62,
      "points_against": 85.8,
      "opponent": "Revy\u2019s Konstruction"
    },
    "week_11": {
      "points_for": 107.26,
      "points_against": 82.0,
      "opponent": "Supernova\u2019s Studs"
    },
    "week_12": {
      "points_for": 111.28,
      "points_against": 121.44,
      "opponent": "Tsuga\u2019s Tuck Shop"
    },
    "week_13": {
      "points_for": 121.16,
      "points_against": 150.34,
      "opponent": "Sparty's Sigmas"
    },
    "week_14": {
      "points_for": 144.24,
      "points_against": 118.06,
      "opponent": "Lawrence & Order"
    },
    "week_15": {
      "points_for": 119.84,
      "points_against": 80.72,
      "opponent": "Revy\u2019s Konstruction"
    },
    "week_16": {
      "points_for": 142.58,
      "points_against": 96.14,
      "opponent": "Oscorps Buns"
    },
    "week_17": {
      "points_for": 107.34,
      "points_against": 144.26,
      "opponent": "Bumpin Brasnos"
    }
  },
  "Oscorps Buns": {
    "week_1": {
      "points_for": 143.2,
      "points_against": 103.24,
      "opponent": "For Pitts and Giggles"
    },
    "week_2": {
      "points_for": 99.42,
      "points_against": 120.84,
      "opponent": "Tsuga\u2019s Tuck Shop"
    },
    "week_3": {
      "points_for": 113.28,
      "points_against": 88.06,
      "opponent": "Supernova\u2019s Studs"
    },
    "week_4": {
      "points_for": 123.26,
      "points_against": 122.54,
      "opponent": "Sparty's Sigmas"
    },
    "week_5": {
      "points_for": 133.02,
      "points_against": 122.24,
      "opponent": "Wicked Wah-Bams"
    },
    "week_6": {
      "points_for": 93.9,
      "points_against": 102.58,
      "opponent": "Revy\u2019s Konstruction"
    },
    "week_7": {
      "points_for": 80.66,
      "points_against": 117.66,
      "opponent": "The Hunters"
    },
    "week_8": {
      "points_for": 111.26,
      "points_against": 129.26,
      "opponent": "For Pitts and Giggles"
    },
    "week_9": {
      "points_for": 99.08,
      "points_against": 159.48,
      "opponent": "Room 40"
    },
    "week_10": {
      "points_for": 100.82,
      "points_against": 103.78,
      "opponent": "The Sage's Playmakers"
    },
    "week_11": {
      "points_for": 136.34,
      "points_against": 147.7,
      "opponent": "Bumpin Brasnos"
    },
    "week_12": {
      "points_for": 153.4,
      "points_against": 114.2,
      "opponent": "Sparty's Sigmas"
    },
    "week_13": {
      "points_for": 121.92,
      "points_against": 116.92,
      "opponent": "Lawrence & Order"
    },
    "week_14": {
      "points_for": 114.38,
      "points_against": 120.14,
      "opponent": "Revy\u2019s Konstruction"
    },
    "week_16": {
      "points_for": 96.14,
      "points_against": 142.58,
      "opponent": "Room 40"
    },
    "week_17": {
      "points_for": 93.18,
      "points_against": 90.28,
      "opponent": "Supernova\u2019s Studs"
    }
  },
  "Supernova\u2019s Studs": {
    "week_1": {
      "points_for": 88.22,
      "points_against": 116.84,
      "opponent": "Wicked Wah-Bams"
    },
    "week_2": {
      "points_for": 101.2,
      "points_against": 135.54,
      "opponent": "The Hunters"
    },
    "week_3": {
      "points_for": 88.06,
      "points_against": 113.28,
      "opponent": "Oscorps Buns"
    },
    "week_4": {
      "points_for": 137.02,
      "points_against": 149.08,
      "opponent": "Bumpin Brasnos"
    },
    "week_5": {
      "points_for": 108.62,
      "points_against": 62.0,
      "opponent": "Lawrence & Order"
    },
    "week_6": {
      "points_for": 140.38,
      "points_against": 116.44,
      "opponent": "The Sage's Playmakers"
    },
    "week_7": {
      "points_for": 123.84,
      "points_against": 105.74,
      "opponent": "Revy\u2019s Konstruction"
    },
    "week_8": {
      "points_for": 129.66,
      "points_against": 106.7,
      "opponent": "Wicked Wah-Bams"
    },
    "week_9": {
      "points_for": 120.02,
      "points_against": 96.62,
      "opponent": "Sparty's Sigmas"
    },
    "week_10": {
      "points_for": 89.46,
      "points_against": 147.36,
      "opponent": "Tsuga\u2019s Tuck Shop"
    },
    "week_11": {
      "points_for": 82.0,
      "points_against": 107.26,
      "opponent": "Room 40"
    },
    "week_12": {
      "points_for": 108.12,
      "points_against": 137.18,
      "opponent": "Bumpin Brasnos"
    },
    "week_13": {
      "points_for": 134.5,
      "points_against": 112.34,
      "opponent": "For Pitts and Giggles"
    },
    "week_14": {
      "points_for": 102.4,
      "points_against": 128.52,
      "opponent": "The Sage's Playmakers"
    },
    "week_15": {
      "points_for": 121.36,
      "points_against": 79.86,
      "opponent": "The Sage's Playmakers"
    },
    "week_16": {
      "points_for": 83.5,
      "points_against": 149.62,
      "opponent": "Bumpin Brasnos"
    },
    "week_17": {
      "points_for": 90.28,
      "points_against": 93.18,
      "opponent": "Oscorps Buns"
    }
  },
  "Revy\u2019s Konstruction": {
    "week_1": {
      "points_for": 98.76,
      "points_against": 82.28,
      "opponent": "Sparty's Sigmas"
    },
    "week_2": {
      "points_for": 86.06,
      "points_against": 128.84,
      "opponent": "Lawrence & Order"
    },
    "week_3": {
      "points_for": 112.86,
      "points_against": 130.54,
      "opponent": "The Hunters"
    },
    "week_4": {
      "points_for": 92.18,
      "points_against": 130.1,
      "opponent": "For Pitts and Giggles"
    },
    "week_5": {
      "points_for": 147.82,
      "points_against": 78.1,
      "opponent": "The Sage's Playmakers"
    },
    "week_6": {
      "points_for": 102.58,
      "points_against": 93.9,
      "opponent": "Oscorps Buns"
    },
    "week_7": {
      "points_for": 105.74,
      "points_against": 123.84,
      "opponent": "Supernova\u2019s Studs"
    },
    "week_8": {
      "points_for": 112.46,
      "points_against": 162.72,
      "opponent": "Sparty's Sigmas"
    },
    "week_9": {
      "points_for": 76.84,
      "points_against": 142.34,
      "opponent": "Bumpin Brasnos"
    },
    "week_10": {
      "points_for": 85.8,
      "points_against": 78.62,
      "opponent": "Room 40"
    },
    "week_11": {
      "points_for": 101.3,
      "points_against": 82.86,
      "opponent": "Tsuga\u2019s Tuck Shop"
    },
    "week_12": {
      "points_for": 101.96,
      "points_against": 145.26,
      "opponent": "For Pitts and Giggles"
    },
    "week_13": {
      "points_for": 111.36,
      "points_against": 117.42,
      "opponent": "Wicked Wah-Bams"
    },
    "week_14": {
      "points_for": 120.14,
      "points_against": 114.38,
      "opponent": "Oscorps Buns"
    },
    "week_15": {
      "points_for": 80.72,
      "points_against": 119.84,
      "opponent": "Room 40"
    },
    "week_16": {
      "points_for": 131.02,
      "points_against": 100.36,
      "opponent": "The Sage's Playmakers"
    }
  },
  "The Sage's Playmakers": {
    "week_1": {
      "points_for": 128.46,
      "points_against": 110.16,
      "opponent": "Bumpin Brasnos"
    },
    "week_2": {
      "points_for": 95.0,
      "points_against": 108.66,
      "opponent": "For Pitts and Giggles"
    },
    "week_3": {
      "points_for": 53.96,
      "points_against": 141.18,
      "opponent": "Room 40"
    },
    "week_4": {
      "points_for": 82.6,
      "points_against": 116.72,
      "opponent": "Wicked Wah-Bams"
    },
    "week_5": {
      "points_for": 78.1,
      "points_against": 147.82,
      "opponent": "Revy\u2019s Konstruction"
    },
    "week_6": {
      "points_for": 116.44,
      "points_against": 140.38,
      "opponent": "Supernova\u2019s Studs"
    },
    "week_7": {
      "points_for": 95.36,
      "points_against": 97.36,
      "opponent": "Tsuga\u2019s Tuck Shop"
    },
    "week_8": {
      "points_for": 152.48,
      "points_against": 123.92,
      "opponent": "Bumpin Brasnos"
    },
    "week_9": {
      "points_for": 93.9,
      "points_against": 84.8,
      "opponent": "Lawrence & Order"
    },
    "week_10": {
      "points_for": 103.78,
      "points_against": 100.82,
      "opponent": "Oscorps Buns"
    },
    "week_11": {
      "points_for": 113.04,
      "points_against": 163.84,
      "opponent": "Sparty's Sigmas"
    },
    "week_12": {
      "points_for": 141.8,
      "points_against": 97.82,
      "opponent": "Wicked Wah-Bams"
    },
    "week_13": {
      "points_for": 93.78,
      "points_against": 133.36,
      "opponent": "The Hunters"
    },
    "week_14": {
      "points_for": 128.52,
      "points_against": 102.4,
      "opponent": "Supernova\u2019s Studs"
    },
    "week_15": {
      "points_for": 79.86,
      "points_against": 121.36,
      "opponent": "Supernova\u2019s Studs"
    },
    "week_16": {
      "points_for": 100.36,
      "points_against": 131.02,
      "opponent": "Revy\u2019s Konstruction"
    }
  }
}